Workbook
Name costab1: Budget!$S$70:$S$71
Name costab2: Budget!$S$70:$S$71,Budget!$Z$70,Budget!$Z$71
Name costab3: Budget!$S$70:$S$71,Budget!$Z$70,Budget!$Z$71,Budget!$AG$70,Budget!$AG$71
Name costab4: Budget!$S$70:$S$71,Budget!$Z$70,Budget!$Z$71,Budget!$AG$70,Budget!$AG$71,Budget!$AO$70,Budget!$AO$71
Name costab5: Budget!$S$70,Budget!$S$71,Budget!$Z$70,Budget!$Z$71,Budget!$AG$70,Budget!$AG$71,Budget!$AO$70,Budget!$AO$71,Budget!$AW$70,Budget!$AW$71
Name costcd1: Budget!$S$72:$S$73
Name costcd2: Budget!$S$72:$S$73,Budget!$Z$72,Budget!$Z$73
Name costcd3: Budget!$S$72:$S$73,Budget!$Z$72,Budget!$Z$73,Budget!$AG$72,Budget!$AG$73
Name costcd4: Budget!$S$72:$S$73,Budget!$Z$72,Budget!$Z$73,Budget!$AG$72,Budget!$AG$73,Budget!$AO$72,Budget!$AO$73
Name costcd5: Budget!$S$72,Budget!$S$73,Budget!$Z$72,Budget!$Z$73,Budget!$AG$72,Budget!$AG$73,Budget!$AO$72,Budget!$AO$73,Budget!$AW$72,Budget!$AW$73
Name costef1: Budget!$S$74:$S$75
Name costef2: Budget!$S$74:$S$75,Budget!$Z$74,Budget!$Z$75
Name costef3: Budget!$S$74:$S$75,Budget!$Z$74,Budget!$Z$75,Budget!$AG$74,Budget!$AG$75
Name costef4: Budget!$S$74,Budget!$S$75,Budget!$Z$74,Budget!$Z$75,Budget!$AG$74,Budget!$AG$75,Budget!$AO$74,Budget!$AO$75
Name costef5: Budget!$S$74,Budget!$S$75,Budget!$Z$74,Budget!$Z$75,Budget!$AG$74,Budget!$AG$75,Budget!$AO$74,Budget!$AO$75,Budget!$AW$74,Budget!$AW$75

Sheet Budget
D2: Principal Investigator: | E2: Kaloyan Penev | T2: Department or Research Unit: | U2: Physics
D4: Sponsor: | E4: NASA ADAP | T4: Project Dates: | V4: 43965 | AA4: through | AE4: 44694 | AU4: through
G6: Merit/Cost of Living Increases: | H6: 0.03
Q7: Year 1 | V7: Year 2 | AC7: Year 3 | AM7: Year 4 | AU7: Year 5
A9: A. | C9: SENIOR PERSONNEL: PI/PD, Co-PI'S, Faculty and Other Senior Associates | O9: Acad FTE | V9: Acad FTE | AC9: Acad FTE | AK9: Acad FTE | AS9: Acad FTE | AZ9: TOTAL FUNDS REQUESTED
C10: FirstName LastName | F10: Monthly Base | H10: Academic Effort | J10: Summer Effort | L10: Fringe Rate | Q10: Sumr FTE | S10: Salary Requested | X10: Sumr FTE | Z10: Salary Requested | AE10: Sumr FTE | AG10: Salary Requested | AM10: Sumr FTE | AO10: Salary Requested | AU10: Sumr FTE | AW10: Salary Requested
B11: 1. | C11: PI Kaloyan Penev | F11: 11712.89 | H11: 0 | J11: 1 | L11: 0.32 | O11: 0 | Q11: 1 | S11: =(IF(O11>0,O11*$F11*$H11*(1+$H$6)^0,0))+(IF(Q11>0,Q11*$F11*$J11*(1+$H$6)^0,0)) -> 11712.89 | V11: 0 | X11: 1 | Z11: =(IF(V11>0,V11*$F11*$H11*(1+$H$6)^1,0))+(IF(X11>0,X11*$F11*$J11*(1+$H$6)^1,0)) -> 12064.277 | AC11: 0 | AE11: 0 | AG11: =(IF(AC11>0,AC11*$F11*$H11*(1+$H$6)^2,0))+(IF(AE11>0,AE11*$F11*$J11*(1+$H$6)^2,0)) -> 0 | AK11: 0 | AM11: 0 | AO11: =(IF(AK11>0,AK11*$F11*$H11*(1+$H$6)^3,0))+(IF(AM11>0,AM11*$F11*$J11*(1+$H$6)^3,0)) -> 0 | AS11: 0 | AU11: 0 | AW11: =(IF(AS11>0,AS11*$F11*$H11*(1+$H$6)^4,0))+(IF(AU11>0,AU11*$F11*$J11*(1+$H$6)^4,0)) -> 0 | AZ11: =SUM(S11+Z11+AG11+AO11+AW11) -> 23777.167
B12: 2. | C12: Co1 | F12: 0 | H12: 0 | J12: 1 | L12: 0.32 | O12: 0 | Q12: 0 | S12: =(IF(O12>0,O12*$F12*$H12*(1+$H$6)^0,0))+(IF(Q12>0,Q12*$F12*$J12*(1+$H$6)^0,0)) -> 0 | V12: 0 | X12: 0 | Z12: =(IF(V12>0,V12*$F12*$H12*(1+$H$6)^1,0))+(IF(X12>0,X12*$F12*$J12*(1+$H$6)^1,0)) -> 0 | AC12: 0 | AE12: 0 | AG12: =(IF(AC12>0,AC12*$F12*$H12*(1+$H$6)^2,0))+(IF(AE12>0,AE12*$F12*$J12*(1+$H$6)^2,0)) -> 0 | AK12: 0 | AM12: 0 | AO12: =(IF(AK12>0,AK12*$F12*$H12*(1+$H$6)^3,0))+(IF(AM12>0,AM12*$F12*$J12*(1+$H$6)^3,0)) -> 0 | AS12: 0 | AU12: 0 | AW12: =(IF(AS12>0,AS12*$F12*$H12*(1+$H$6)^4,0))+(IF(AU12>0,AU12*$F12*$J12*(1+$H$6)^4,0)) -> 0 | AZ12: =SUM(S12+Z12+AG12+AO12+AW12) -> 0
B13: 3. | C13: Co2 | F13: 0 | H13: 0 | J13: 1 | L13: 0.32 | O13: 0 | Q13: 0 | S13: =(IF(O13>0,O13*$F13*$H13*(1+$H$6)^0,0))+(IF(Q13>0,Q13*$F13*$J13*(1+$H$6)^0,0)) -> 0 | V13: 0 | X13: 0 | Z13: =(IF(V13>0,V13*$F13*$H13*(1+$H$6)^1,0))+(IF(X13>0,X13*$F13*$J13*(1+$H$6)^1,0)) -> 0 | AC13: 0 | AE13: 0 | AG13: =(IF(AC13>0,AC13*$F13*$H13*(1+$H$6)^2,0))+(IF(AE13>0,AE13*$F13*$J13*(1+$H$6)^2,0)) -> 0 | AK13: 0 | AM13: 0 | AO13: =(IF(AK13>0,AK13*$F13*$H13*(1+$H$6)^3,0))+(IF(AM13>0,AM13*$F13*$J13*(1+$H$6)^3,0)) -> 0 | AS13: 0 | AU13: 0 | AW13: =(IF(AS13>0,AS13*$F13*$H13*(1+$H$6)^4,0))+(IF(AU13>0,AU13*$F13*$J13*(1+$H$6)^4,0)) -> 0 | AZ13: =SUM(S13+Z13+AG13+AO13+AW13) -> 0
B14: 4. | C14: Co3 | F14: 0 | H14: 0 | J14: 1 | L14: 0.32 | O14: 0 | Q14: 0 | S14: =(IF(O14>0,O14*$F14*$H14*(1+$H$6)^0,0))+(IF(Q14>0,Q14*$F14*$J14*(1+$H$6)^0,0)) -> 0 | V14: 0 | X14: 0 | Z14: =(IF(V14>0,V14*$F14*$H14*(1+$H$6)^1,0))+(IF(X14>0,X14*$F14*$J14*(1+$H$6)^1,0)) -> 0 | AC14: 0 | AE14: 0 | AG14: =(IF(AC14>0,AC14*$F14*$H14*(1+$H$6)^2,0))+(IF(AE14>0,AE14*$F14*$J14*(1+$H$6)^2,0)) -> 0 | AK14: 0 | AM14: 0 | AO14: =(IF(AK14>0,AK14*$F14*$H14*(1+$H$6)^3,0))+(IF(AM14>0,AM14*$F14*$J14*(1+$H$6)^3,0)) -> 0 | AS14: 0 | AU14: 0 | AW14: =(IF(AS14>0,AS14*$F14*$H14*(1+$H$6)^4,0))+(IF(AU14>0,AU14*$F14*$J14*(1+$H$6)^4,0)) -> 0 | AZ14: =SUM(S14+Z14+AG14+AO14+AW14) -> 0
B15: 5. | C15: Co4 | F15: 0 | H15: 0 | J15: 1 | L15: 0.32 | O15: 0 | Q15: 0 | S15: =(IF(O15>0,O15*$F15*$H15*(1+$H$6)^0,0))+(IF(Q15>0,Q15*$F15*$J15*(1+$H$6)^0,0)) -> 0 | V15: 0 | X15: 0 | Z15: =(IF(V15>0,V15*$F15*$H15*(1+$H$6)^1,0))+(IF(X15>0,X15*$F15*$J15*(1+$H$6)^1,0)) -> 0 | AC15: 0 | AE15: 0 | AG15: =(IF(AC15>0,AC15*$F15*$H15*(1+$H$6)^2,0))+(IF(AE15>0,AE15*$F15*$J15*(1+$H$6)^2,0)) -> 0 | AK15: 0 | AM15: 0 | AO15: =(IF(AK15>0,AK15*$F15*$H15*(1+$H$6)^3,0))+(IF(AM15>0,AM15*$F15*$J15*(1+$H$6)^3,0)) -> 0 | AS15: 0 | AU15: 0 | AW15: =(IF(AS15>0,AS15*$F15*$H15*(1+$H$6)^4,0))+(IF(AU15>0,AU15*$F15*$J15*(1+$H$6)^4,0)) -> 0 | AZ15: =SUM(S15+Z15+AG15+AO15+AW15) -> 0
B16: 6. | C16: Senior Personnel | F16: 0 | H16: 0 | J16: 1 | L16: 0.32 | O16: 0 | Q16: 0 | S16: =(IF(O16>0,O16*$F16*$H16*(1+$H$6)^0,0))+(IF(Q16>0,Q16*$F16*$J16*(1+$H$6)^0,0)) -> 0 | V16: 0 | X16: 0 | Z16: =(IF(V16>0,V16*$F16*$H16*(1+$H$6)^1,0))+(IF(X16>0,X16*$F16*$J16*(1+$H$6)^1,0)) -> 0 | AC16: 0 | AE16: 0 | AG16: =(IF(AC16>0,AC16*$F16*$H16*(1+$H$6)^2,0))+(IF(AE16>0,AE16*$F16*$J16*(1+$H$6)^2,0)) -> 0 | AK16: 0 | AM16: 0 | AO16: =(IF(AK16>0,AK16*$F16*$H16*(1+$H$6)^3,0))+(IF(AM16>0,AM16*$F16*$J16*(1+$H$6)^3,0)) -> 0 | AS16: 0 | AU16: 0 | AW16: =(IF(AS16>0,AS16*$F16*$H16*(1+$H$6)^4,0))+(IF(AU16>0,AU16*$F16*$J16*(1+$H$6)^4,0)) -> 0 | AZ16: =SUM(S16+Z16+AG16+AO16+AW16) -> 0
C17: TOTAL SENIOR PERSONNEL | S17: =SUM(S11:S16) -> 11712.89 | Z17: =SUM(Z11:Z16) -> 12064.277 | AG17: =SUM(AG11:AG16) -> 0 | AO17: =SUM(AO11:AO16) -> 0 | AW17: =SUM(AW11:AW16) -> 0 | AZ17: =SUM(AZ11:AZ16) -> 23777.167
A19: B. | B19: OTHER PERSONNEL (SHOW NUMBERS IN BOXES) | F19: Monthly Base | J19: Calendar Effort | L19: Fringe Rate | Q19: Cal Effort | X19: Cal Effort | AE19: Cal Effort | AM19: Cal Effort | AU19: Cal Effort
B20: 1. | C20: 0 | D20: Post Doctoral Associates | F20: 0 | J20: 1 | L20: 0.32 | Q20: 0 | S20: =(IF(Q20>0,Q20*$F20*$J20*(1+$H$6)^0,0)) -> 0 | X20: 0 | Z20: =(IF(X20>0,X20*$F20*$J20*(1+$H$6)^1,0)) -> 0 | AE20: 0 | AG20: =(IF(AE20>0,AE20*$F20*$J20*(1+$H$6)^2,0)) -> 0 | AM20: 0 | AO20: =(IF(AM20>0,AM20*$F20*$J20*(1+$H$6)^3,0)) -> 0 | AU20: 0 | AW20: =(IF(AU20>0,AU20*$F20*$J20*(1+$H$6)^4,0)) -> 0 | AZ20: =SUM(S20+Z20+AG20+AO20+AW20) -> 0
B21: 2. | C21: 0 | D21: Other (having the same monthly base) | F21: 0 | J21: 1 | L21: 0.32 | Q21: 0 | S21: =(IF(Q21>0,Q21*$F21*$J21*(1+$H$6)^0,0)) -> 0 | X21: 0 | Z21: =(IF(X21>0,X21*$F21*$J21*(1+$H$6)^1,0)) -> 0 | AE21: 0 | AG21: =(IF(AE21>0,AE21*$F21*$J21*(1+$H$6)^2,0)) -> 0 | AM21: 0 | AO21: =(IF(AM21>0,AM21*$F21*$J21*(1+$H$6)^3,0)) -> 0 | AU21: 0 | AW21: =(IF(AU21>0,AU21*$F21*$J21*(1+$H$6)^4,0)) -> 0 | AZ21: =SUM(S21+Z21+AG21+AO21+AW21) -> 0
B22: 3. | C22: 1 | D22: Graduate Students | F22: 2400 | J22: 1 | L22: 0.25 | Q22: 12 | S22: =(IF(Q22>0,Q22*$F22*$J22*(1+$H$6)^0,0)) -> 28800 | X22: 12 | Z22: =(IF(X22>0,X22*$F22*$J22*(1+$H$6)^1,0)) -> 29664 | AE22: 0 | AG22: =(IF(AE22>0,AE22*$F22*$J22*(1+$H$6)^2,0)) -> 0 | AM22: 0 | AO22: =(IF(AM22>0,AM22*$F22*$J22*(1+$H$6)^3,0)) -> 0 | AU22: 0 | AW22: =(IF(AU22>0,AU22*$F22*$J22*(1+$H$6)^4,0)) -> 0 | AZ22: =SUM(S22+Z22+AG22+AO22+AW22) -> 58464
B23: 4. | C23: 0 | D23: Undergraduate Students | F23: 0 | J23: 1 | L23: 0.05 | Q23: 0 | S23: =(IF(Q23>0,Q23*$F23*$J23*(1+$H$6)^0,0)) -> 0 | X23: 0 | Z23: =(IF(X23>0,X23*$F23*$J23*(1+$H$6)^1,0)) -> 0 | AE23: 0 | AG23: =(IF(AE23>0,AE23*$F23*$J23*(1+$H$6)^2,0)) -> 0 | AM23: 0 | AO23: =(IF(AM23>0,AM23*$F23*$J23*(1+$H$6)^3,0)) -> 0 | AU23: 0 | AW23: =(IF(AU23>0,AU23*$F23*$J23*(1+$H$6)^4,0)) -> 0 | AZ23: =SUM(S23+Z23+AG23+AO23+AW23) -> 0
B24: 5. | C24: 0 | D24: Administrative (If Charged Directly) | F24: 0 | J24: 1 | L24: 0.32 | Q24: 0 | S24: =(IF(Q24>0,Q24*$F24*$J24*(1+$H$6)^0,0)) -> 0 | X24: 0 | Z24: =(IF(X24>0,X24*$F24*$J24*(1+$H$6)^1,0)) -> 0 | AE24: 0 | AG24: =(IF(AE24>0,AE24*$F24*$J24*(1+$H$6)^2,0)) -> 0 | AM24: 0 | AO24: =(IF(AM24>0,AM24*$F24*$J24*(1+$H$6)^3,0)) -> 0 | AU24: 0 | AW24: =(IF(AU24>0,AU24*$F24*$J24*(1+$H$6)^4,0)) -> 0 | AZ24: =SUM(S24+Z24+AG24+AO24+AW24) -> 0
B25: 6. | C25: 0 | D25: Other (Not having the same base salary) | F25: 0 | J25: 1 | L25: 0.32 | Q25: 0 | S25: =(IF(Q25>0,Q25*$F25*$J25*(1+$H$6)^0,0)) -> 0 | X25: 0 | Z25: =(IF(X25>0,X25*$F25*$J25*(1+$H$6)^1,0)) -> 0 | AE25: 0 | AG25: =(IF(AE25>0,AE25*$F25*$J25*(1+$H$6)^2,0)) -> 0 | AM25: 0 | AO25: =(IF(AM25>0,AM25*$F25*$J25*(1+$H$6)^3,0)) -> 0 | AU25: 0 | AW25: =(IF(AU25>0,AU25*$F25*$J25*(1+$H$6)^4,0)) -> 0 | AZ25: =SUM(S25+Z25+AG25+AO25+AW25) -> 0
C26: TOTAL OTHER PERSONNEL | S26: =SUM(S20:S25) -> 28800 | Z26: =SUM(Z20:Z25) -> 29664 | AG26: =SUM(AG20:AG25) -> 0 | AO26: =SUM(AO20:AO25) -> 0 | AW26: =SUM(AW20:AW25) -> 0 | AZ26: =SUM(AZ20:AZ25) -> 58464
C28: TOTAL SALARIES AND WAGES (A+B) | S28: =S17+S26 -> 40512.89 | Z28: =Z17+Z26 -> 41728.277 | AG28: =AG17+AG26 -> 0 | AO28: =AO17+AO26 -> 0 | AW28: =AW17+AW26 -> 0 | AZ28: =AZ17+AZ26 -> 82241.167
A30: C. | B30: FRINGE BENEFITS (AUTOMATICALLY CALCULATED BASED ON ENTERED RATES)
B31: 1. | C31: Senior Personnel | F31: =C11 -> PI Kaloyan Penev | S31: =S11*L11 -> 3748.1248 | Z31: =Z11*L11 -> 3860.5685 | AG31: =AG11*L11 -> 0 | AO31: =AO11*L11 -> 0 | AW31: =AW11*L11 -> 0 | AZ31: =SUM(S31+Z31+AG31+AO31+AW31) -> 7608.6933
B32: 2. | C32: Senior Personnel | F32: =C12 -> Co1 | S32: =S12*L12 -> 0 | Z32: =Z12*L12 -> 0 | AG32: =AG12*L12 -> 0 | AO32: =AO12*L12 -> 0 | AW32: =AW12*L12 -> 0 | AZ32: =SUM(S32+Z32+AG32+AO32+AW32) -> 0
B33: 3. | C33: Senior Personnel | F33: =C13 -> Co2 | S33: =S13*L13 -> 0 | Z33: =Z13*L13 -> 0 | AG33: =AG13*L13 -> 0 | AO33: =AO13*L13 -> 0 | AW33: =AW13*L13 -> 0 | AZ33: =SUM(S33+Z33+AG33+AO33+AW33) -> 0
B34: 4 | C34: Senior Personnel | F34: =C14 -> Co3 | S34: =S14*L14 -> 0 | Z34: =Z14*L14 -> 0 | AG34: =AG14*L14 -> 0 | AO34: =AO14*L14 -> 0 | AW34: =AW14*L14 -> 0 | AZ34: =SUM(S34+Z34+AG34+AO34+AW34) -> 0
B35: 5 | C35: Senior Personnel | F35: =C15 -> Co4 | S35: =S15*L15 -> 0 | Z35: =Z15*L15 -> 0 | AG35: =AG15*L15 -> 0 | AO35: =AO15*L15 -> 0 | AW35: =AW15*L15 -> 0 | AZ35: =SUM(S35+Z35+AG35+AO35+AW35) -> 0
B36: 6. | C36: Senior Personnel | F36: =C16 -> Senior Personnel | S36: =S16*L16 -> 0 | Z36: =Z16*L16 -> 0 | AG36: =AG16*L16 -> 0 | AO36: =AO16*L16 -> 0 | AW36: =AW16*L16 -> 0 | AZ36: =SUM(S36+Z36+AG36+AO36+AW36) -> 0
B37: 1. | C37: Other Personnel - Post Doctoral Associates | S37: =S20*L20 -> 0 | Z37: =Z20*L20 -> 0 | AG37: =AG20*L20 -> 0 | AO37: =AO20*L20 -> 0 | AW37: =AW20*L20 -> 0 | AZ37: =SUM(S37+Z37+AG37+AO37+AW37) -> 0
B38: 2. | C38: Other Personnel - Other (having the same monthly base salary) | S38: =S21*L21 -> 0 | Z38: =Z21*L21 -> 0 | AG38: =AG21*L21 -> 0 | AO38: =AO21*L21 -> 0 | AW38: =AW21*L21 -> 0 | AZ38: =SUM(S38+Z38+AG38+AO38+AW38) -> 0
B39: 3. | C39: Other Personnel - Graduate Students (includes insurance premiums) | S39: =(S22*L22)+('GRA Insurance'!A2*Q22) -> 10512.96 | Z39: =(Z22*L22)+('GRA Insurance'!B2*X22) -> 10894.608 | AG39: =(AG22*L22)+('GRA Insurance'!C2*AE22) -> 0 | AO39: =(AO22*L22)+('GRA Insurance'!D2*AM22) -> 0 | AW39: =(AW22*L22)+('GRA Insurance'!E2*AU22) -> 0 | AZ39: =SUM(S39+Z39+AG39+AO39+AW39) -> 21407.568
B40: 4. | C40: Other Personnel - Undergraduate Students | S40: =S23*L23 -> 0 | Z40: =Z23*L23 -> 0 | AG40: =AG23*L23 -> 0 | AO40: =AO23*L23 -> 0 | AW40: =AW23*L23 -> 0 | AZ40: =SUM(S40+Z40+AG40+AO40+AW40) -> 0
B41: 5. | C41: Other Personnel - Administrative (If Charged Directly) | S41: =S24*L24 -> 0 | Z41: =Z24*L24 -> 0 | AG41: =AG24*L24 -> 0 | AO41: =AO24*L24 -> 0 | AW41: =AW24*L24 -> 0 | AZ41: =SUM(S41+Z41+AG41+AO41+AW41) -> 0
B42: 6. | C42: Other Personnel - Other (Not having the same base salary) | S42: =S25*L25 -> 0 | Z42: =Z25*L25 -> 0 | AG42: =AG25*L25 -> 0 | AO42: =AO25*L25 -> 0 | AW42: =AW25*L25 -> 0 | AZ42: =SUM(S42+Z42+AG42+AO42+AW42) -> 0
C43: TOTAL FRINGE BENEFITS | S43: =SUM(S31:S42) -> 14261.085 | Z43: =SUM(Z31:Z42) -> 14755.177 | AG43: =SUM(AG31:AG42) -> 0 | AO43: =SUM(AO31:AO42) -> 0 | AW43: =SUM(AW31:AW42) -> 0 | AZ43: =SUM(AZ31:AZ42) -> 29016.261
C45: TOTAL SALARIES, WAGES AND FRINGE BENEFITS (A+B+C) | S45: =SUM(S28+S43) -> 54773.975 | Y45: =SUM(Y28+Y43) -> 0 | Z45: =SUM(Z28+Z43) -> 56483.453 | AF45: =SUM(AF28+AF43) -> 0 | AG45: =SUM(AG28+AG43) -> 0 | AN45: =SUM(AN28+AN43) -> 0 | AO45: =SUM(AO28+AO43) -> 0 | AV45: =SUM(AV28+AV43) -> 0 | AW45: =SUM(AW28+AW43) -> 0 | AZ45: =SUM(S45+Z45+AG45+AO45+AW45) -> 111257.43
A47: D. | B47: PERMANENT EQUIPMENT (LIST ITEM AND DOLLAR AMOUNT FOR EACH ITEM EXCEEDING $5000) (Exempt from IDC)
C48: equipment item 1 | S48: 0 | Z48: 0 | AG48: 0 | AO48: 0 | AW48: 0 | AZ48: =SUM(S48+Z48+AG48+AO48+AW48) -> 0
C49: equipment item 2 | S49: 0 | Z49: 0 | AG49: 0 | AO49: 0 | AW49: 0 | AZ49: =SUM(S49+Z49+AG49+AO49+AW49) -> 0
C50: equipment item 3 | S50: 0 | Z50: 0 | AG50: 0 | AO50: 0 | AW50: 0 | AZ50: =SUM(S50+Z50+AG50+AO50+AW50) -> 0
C51: TOTAL PERMANENT EQUIPMENT | S51: =SUM(S48:S50) -> 0 | Y51: =SUM(Y34+Y49) -> 0 | Z51: =SUM(Z48:Z50) -> 0 | AF51: =SUM(AF34+AF49) -> 0 | AG51: =SUM(AG48:AG50) -> 0 | AN51: =SUM(AN34+AN49) -> 0 | AO51: =SUM(AO48:AO50) -> 0 | AV51: =SUM(AV34+AV49) -> 0 | AW51: =SUM(AW48:AW50) -> 0 | AZ51: =SUM(S51+Z51+AG51+AO51+AW51) -> 0
A52: E. | B52: TRAVEL
B53: 1. | C53: Domestic | S53: 4435 | Z53: 4435 | AG53: 0 | AO53: 0 | AW53: 0 | AZ53: =SUM(S53+Z53+AG53+AO53+AW53) -> 8870
B54: 2. | C54: Foreign | S54: 0 | Z54: 0 | AG54: 0 | AO54: 0 | AW54: 0 | AZ54: =SUM(S54+Z54+AG54+AO54+AW54) -> 0
C55: TOTAL TRAVEL | S55: =SUM(S53:S54) -> 4435 | Z55: =SUM(Z53:Z54) -> 4435 | AG55: =SUM(AG53:AG54) -> 0 | AO55: =SUM(AO53:AO54) -> 0 | AW55: =SUM(AW53:AW54) -> 0 | AZ55: =SUM(AZ53:AZ54) -> 8870
A57: F. | B57: PARTICIPANT SUPPORT COSTS (Exempt from IDC)
B58: 1. | C58: Stipends | L58: Yes | S58: =0 -> 0 | Z58: 0 | AG58: 0 | AO58: 0 | AW58: 0 | AZ58: =SUM(S58+Z58+AG58+AO58+AW58) -> 0
B59: 2. | C59: Travel | L59: Yes | S59: =0 -> 0 | Z59: 0 | AG59: 0 | AO59: 0 | AW59: 0 | AZ59: =SUM(S59+Z59+AG59+AO59+AW59) -> 0
B60: 3. | C60: Subsistence | L60: Yes | S60: 0 | Z60: 0 | AG60: 0 | AO60: 0 | AW60: 0 | AZ60: =SUM(S60+Z60+AG60+AO60+AW60) -> 0
B61: 4. | C61: Other | L61: Yes | S61: 0 | Z61: 0 | AG61: 0 | AO61: 0 | AW61: 0 | AZ61: =SUM(S61+Z61+AG61+AO61+AW61) -> 0
D62: TOTAL NUMBER OF PARTICIPANTS | S62: =SUM(S58:S61) -> 0 | Z62: =SUM(Z58:Z61) -> 0 | AG62: =SUM(AG58:AG61) -> 0 | AO62: =SUM(AO58:AO61) -> 0 | AW62: =SUM(AW58:AW61) -> 0 | AZ62: =SUM(AZ58:AZ61) -> 0
A64: G. | B64: OTHER DIRECT COSTS
B65: 1. | C65: Materials and Supplies | S65: 0 | Z65: 0 | AG65: 0 | AO65: 0 | AW65: 0 | AZ65: =SUM(S65+Z65+AG65+AO65+AW65) -> 0
B66: 2. | C66: Publication Costs / Documentation / Dissemination | S66: 1900 | Z66: =1900 * 3 -> 5700 | AG66: 0 | AO66: 0 | AW66: 0 | AZ66: =SUM(S66+Z66+AG66+AO66+AW66) -> 7600
B67: 3. | C67: Consultant Services | S67: 0 | Z67: 0 | AG67: 0 | AO67: 0 | AW67: 0 | AZ67: =SUM(S67+Z67+AG67+AO67+AW67) -> 0
B68: 4. | C68: Animal and Animal Care | S68: 0 | Z68: 0 | AG68: 0 | AO68: 0 | AW68: 0 | AZ68: =SUM(S68+Z68+AG68+AO68+AW68) -> 0
B69: 5. | C69: Subawards (IDC on first $25,000 of each subcontract0
C70: a) | D70: Sub 1 direct costs | S70: 0 | Z70: 0 | AG70: 0 | AO70: 0 | AW70: 0 | AZ70: =SUM(S70+Z70+AG70+AO70+AW70) -> 0
C71: b) | D71: Sub 1 indirect costs | S71: 0 | Z71: 0 | AG71: 0 | AO71: 0 | AW71: 0 | AZ71: =SUM(S71+Z71+AG71+AO71+AW71) -> 0
C72: c) | D72: Sub 2 direct costs | S72: 0 | Z72: 0 | AG72: 0 | AO72: 0 | AW72: 0 | AZ72: =SUM(S72+Z72+AG72+AO72+AW72) -> 0
C73: d) | D73: Sub 2 indirect costs | S73: 0 | Z73: 0 | AG73: 0 | AO73: 0 | AW73: 0 | AZ73: =SUM(S73+Z73+AG73+AO73+AW73) -> 0
C74: e) | D74: Sub 3 direct costs | S74: 0 | Z74: 0 | AG74: 0 | AO74: 0 | AW74: 0 | AZ74: =SUM(S74+Z74+AG74+AO74+AW74) -> 0
C75: f) | D75: Sub 3 indirect costs | S75: 0 | Z75: 0 | AG75: 0 | AO75: 0 | AW75: 0 | AZ75: =SUM(S75+Z75+AG75+AO75+AW75) -> 0
B77: 6. | C77: Tuition (Exempt from IDC) | S77: 0 | Z77: 0 | AG77: 0 | AO77: 0 | AW77: 0 | AZ77: =SUM(S77+Z77+AG77+AO77+AW77) -> 0
B78: 7. | C78: Human Subject/Patient Costs | S78: 0 | Z78: 0 | AG78: 0 | AO78: 0 | AW78: 0 | AZ78: =SUM(S78+Z78+AG78+AO78+AW78) -> 0
B79: 8. | C79: Other | S79: 0 | Z79: 0 | AG79: 0 | AO79: 0 | AW79: 0 | AZ79: =SUM(S79+Z79+AG79+AO79+AW79) -> 0
B80: 9. | C80: Other | S80: 0 | Z80: 0 | AG80: 0 | AO80: 0 | AW80: 0 | AZ80: =SUM(S80+Z80+AG80+AO80+AW80) -> 0
C81: TOTAL OTHER DIRECT COSTS | S81: =SUM(S65:S80) -> 1900 | Z81: =SUM(Z65:Z80) -> 5700 | AG81: =SUM(AG65:AG80) -> 0 | AO81: =SUM(AO65:AO80) -> 0 | AW81: =SUM(AW65:AW80) -> 0 | AZ81: =SUM(AZ65:AZ80) -> 7600
A83: H. | B83: TOTAL DIRECT COSTS (A THROUGH G) | S83: =SUM(S45+S51+S55+S62+S81) -> 61108.975 | Z83: =SUM(Z45+Z51+Z55+Z62+Z81) -> 66618.453 | AG83: =SUM(AG45+AG51+AG55+AG62+AG81) -> 0 | AO83: =SUM(AO45+AO51+AO55+AO62+AO81) -> 0 | AW83: =SUM(AW45+AW51+AW55+AW62+AW81) -> 0 | AZ83: =SUM(S83+Z83+AG83+AO83+AW83) -> 127727.43
A85: J. | B85: INDIRECT COSTS
F86: Modified Total Direct Cost (MTDC) Rate: | L86: 0.56 | S86: =IF($L86>0,SUM(S83-S77-S51-OR($L$58="Yes",ISBLANK($L$58))*S58-OR($L$59="Yes",ISBLANK($L$59))*S59-OR($L$60="Yes",ISBLANK($L$60))*S60-OR($L$61="Yes",ISBLANK($L$61))*S61-S105,0),0) -> 61108.975 | Z86: =IF($L86>0,SUM(Z83-Z77-Z51-OR($L$58="yes",ISBLANK($L$58))*Z58-OR($L$59="yes",ISBLANK($L$59))*Z59-OR($L$60="yes",ISBLANK($L$60))*Z60-OR($L$61="yes",ISBLANK($L$61))*Z61-Z105,0),0) -> 66618.453 | AG86: =IF($L86>0,SUM(AG83-AG77-AG51-OR($L$58="yes",ISBLANK($L$58))*AG58-OR($L$59="yes",ISBLANK($L$59))*AG59-OR($L$60="yes",ISBLANK($L$60))*AG60-OR($L$61="yes",ISBLANK($L$61))*AG61-AG105,0),0) -> 0 | AO86: =IF($L86>0,SUM(AO83-AO77-AO51-OR($L$58="yes",ISBLANK($L$58))*AO58-OR($L$59="yes",ISBLANK($L$59))*AO59-OR($L$60="yes",ISBLANK($L$60))*AO60-OR($L$61="yes",ISBLANK($L$61))*AO61-AO105,0),0) -> 0 | AW86: =IF($L86>0,SUM(AW83-AW77-AW51-OR($L$58="yes",ISBLANK($L$58))*AW58-OR($L$59="yes",ISBLANK($L$59))*AW59-OR($L$60="yes",ISBLANK($L$60))*AW60-OR($L$61="yes",ISBLANK($L$61))*AW61-AW105,0),0) -> 0 | AZ86: =SUM(S86+Z86+AG86+AO86+AW86) -> 127727.43
F87: Total Direct Cost (TDC) Rate: | L87: 0 | S87: =IF($L87>0,S83*$L87,0) -> 0 | Z87: =IF($L87>0,Z83*$L87,0) -> 0 | AG87: =IF($L87>0,AG83*$L87,0) -> 0 | AO87: =IF($L87>0,AO83*$L87,0) -> 0 | AW87: =IF($L87>0,AW83*$L87,0) -> 0 | AZ87: =SUM(S87+Z87+AG87+AO87+AW87) -> 0
B88: TOTAL INDIRECT COSTS (F&A) [MTDC Rate * MTDC + TDC Rate * TDC] | S88: =S86*$L86+S87 -> 34221.026 | Z88: =Z86*$L86+Z87 -> 37306.334 | AG88: =AG86*$L86+AG87 -> 0 | AO88: =AO86*$L86+AO87 -> 0 | AW88: =AW86*$L86+AW87 -> 0 | AZ88: =SUM(S88+Z88+AG88+AO88+AW88) -> 71527.36
B89: TOTAL SUBAWARD INDIRECT COSTS | S89: =S71+S73+S75 -> 0 | Z89: =Z71+Z73+Z75 -> 0 | AG89: =AG71+AG73+AG75 -> 0 | AO89: =AO71+AO73+AO75 -> 0 | AW89: =AW71+AW73+AW75 -> 0 | AZ89: =SUM(S89+Z89+AG89+AO89+AW89) -> 0
A90: K. | B90: TOTAL COSTS | S90: =SUM(S83+S88) -> 95330.001 | Z90: =SUM(Z83+Z88) -> 103924.79 | AG90: =SUM(AG83+AG88) -> 0 | AO90: =SUM(AO83+AO88) -> 0 | AW90: =SUM(AW83+AW88) -> 0 | AZ90: =SUM(AZ83+AZ88) -> 199254.79
F92: Column1
C93: Column1 | L93: Column1
C94: Yes
C95: No
S105: =SUM(V106:V108) -> 0 | Z105: =SUM(AC106:AC108) -> 0 | AG105: =SUM(AK106:AK108) -> 0 | AO105: =SUM(AS106:AS108) -> 0 | AW105: =SUM(AZ106:AZ108) -> 0
S106: =SUM(costab1) -> 0 | V106: =IF(S106>25000,S106-25000,0) -> 0 | Z106: =SUM(costab2) -> 0 | AC106: =IF(S106<25000,IF(Z106>25000,SUM(Z70:Z71)-(25000-S106),0),SUM(Z70:Z71)) -> 0 | AG106: =SUM(costab3) -> 0 | AK106: =IF(Z106<25000,IF(AG106>25000,SUM(AG70:AG71)-(25000-Z106),0),SUM(AG70:AG71)) -> 0 | AO106: =SUM(costab4) -> 0 | AS106: =IF(AG106<25000,IF(AO106>25000,SUM(AO70:AO71)-(25000-AG106),0),SUM(AO70:AO71)) -> 0 | AW106: =SUM(costab5) -> 0 | AZ106: =IF(AO106<25000,IF(AW106>25000,SUM(AW70:AW71)-(25000-AO106),0),SUM(AW70:AW71)) -> 0
S107: =SUM(costcd1) -> 0 | V107: =IF(S107>25000,S107-25000,0) -> 0 | Z107: =SUM(costcd2) -> 0 | AC107: =IF(S107<25000,IF(Z107>25000,SUM(Z72:Z73)-(25000-S107),0),SUM(Z72:Z73)) -> 0 | AG107: =SUM(costcd3) -> 0 | AK107: =IF(Z107<25000,IF(AG107>25000,SUM(AG72:AG73)-(25000-Z107),0),SUM(AG72:AG73)) -> 0 | AO107: =SUM(costcd4) -> 0 | AS107: =IF(AG107<25000,IF(AO107>25000,SUM(AO72:AO73)-(25000-AG107),0),SUM(AO72:AO73)) -> 0 | AW107: =SUM(costcd5) -> 0 | AZ107: =IF(AO107<25000,IF(AW107>25000,SUM(AW72:AW73)-(25000-AO107),0),SUM(AW72:AW73)) -> 0
S108: =SUM(costef1) -> 0 | V108: =IF(S108>25000,S108-25000,0) -> 0 | Z108: =SUM(costef2) -> 0 | AC108: =IF(S108<25000,IF(Z108>25000,SUM(Z74:Z75)-(25000-S108),0),SUM(Z74:Z75)) -> 0 | AG108: =SUM(costef3) -> 0 | AK108: =IF(Z108<25000,IF(AG108>25000,SUM(AG74:AG75)-(25000-Z108),0),SUM(AG74:AG75)) -> 0 | AO108: =SUM(costef4) -> 0 | AS108: =IF(AG108<25000,IF(AO108>25000,SUM(AO74:AO75)-(25000-AG108),0),SUM(AO74:AO75)) -> 0 | AW108: =SUM(costef5) -> 0 | AZ108: =IF(AO108<25000,IF(AW108>25000,SUM(AW74:AW75)-(25000-AO108),0),SUM(AW74:AW75)) -> 0
E110: 1

Sheet GRA Insurance
A1: FY23 | B1: FY24 | C1: FY25 | D1: FY26 | E1: FY27 | F1: FY28 | G1: FY29 | H1: FY30 | I1: FY31 | J1: FY32
A2: 276.08 | B2: =(A2*0.05)+A2 -> 289.884 | C2: =(B2*0.05)+B2 -> 304.3782 | D2: =(C2*0.05)+C2 -> 319.59711 | E2: =(D2*0.05)+D2 -> 335.57697 | F2: =(E2*0.05)+E2 -> 352.35581 | G2: =(F2*0.05)+F2 -> 369.9736 | H2: =(G2*0.05)+G2 -> 388.47228 | I2: =(H2*0.05)+H2 -> 407.8959 | J2: =(I2*0.05)+I2 -> 428.29069
A8: Per month/per student
A9: Assumes 5% escalation
A10: Must be appointed for 20 hours minimum
A11: *For project start dates of June 2023 onwards, begin with FY24 rates in year 1
A12: *Calendar month effort mut be accurate for formula to calculate correctly
A13: *Formula only established for graduate students in row 22

Sheet GRA Rates FY23
A1: School | B1: Dept | C1: Monthly rate | E1: Basis
C2: Recommended | D2: Maximum
A3: BBS
B4: All Depts | C4: 2196 | E4: NIH NRSA Levels - https://researchtraining.nih.gov/programs/training-grants
A6: ECS
B7: BioEng | C7: 2225 | D7: 3000
B8: CompSci | C8: 2102 | D8: 2833
B9: Elec Eng | C9: 2063 | D9: 3100
B10: Mech Eng | C10: 2125 | D10: 2800
B11: Materials Sci | C11: 2150 | D11: 2300
B12: System Eng | C12: 2250 | D12: 2550
A14: EPPS
B15: All Depts | C15: 2000
A18: NSM
B19: All Depts | C19: 2100
A22: ATEC
B23: All Depts | C23: 2000
A26: A&H
B27: All Depts | C27: 1662
